qiyin_mcp_demo/__init__.py
qiyin_mcp_demo-0.1.0.dist-info/WHEEL
qiyin_mcp_demo-0.1.0.dist-info/entry_points.txt
qiyin_mcp_demo-0.1.0.dist-info/METADATA
qiyin_mcp_demo-0.1.0.dist-info/RECORD
