Metadata-Version: 2.3
Name: qiyin-mcp-demo
Version: 0.1.0
Summary: Add your description here
Author: 'zhouding'
Author-email: 'zhouding' <706762705@qq.com>
Requires-Dist: mcp[cli]>=1.13.1
Requires-Python: >=3.13
